Metadata-Version: 2.1
Name: gmail-forwarding
Version: 0.0.1
Summary: Automatic Forwarding of Selected Emails using Gmail API - with Subscription
Home-page: https://github.com/FrenchCommando/gmail-forwarding
Author: FrenchCommando
Author-email: martialren@gmail.com
License: UNKNOWN
Keywords: gmail-api,subscription,forwarding
Platform: UNKNOWN
Classifier: Programming Language :: Python :: 3.7
Classifier: License :: OSI Approved :: MIT License
Classifier: Operating System :: OS Independent
Requires-Python: >=3
